weclimb_correlation_module/__init__.py
weclimb_correlation_module/core.py
weclimb_correlation_module-0.1.0.dist-info/METADATA
weclimb_correlation_module-0.1.0.dist-info/WHEEL
weclimb_correlation_module-0.1.0.dist-info/top_level.txt
weclimb_correlation_module-0.1.0.dist-info/RECORD
