Metadata-Version: 2.1
Name: weclimb_correlation_module
Version: 0.1.0
Summary: A module for climate data correlation analysis
Home-page: https://github.com/shiv3679/weclimb_modules
Author: Shiv Shankar Singh
Author-email: shivshankarsingh.py@gmail.com
License: GPL-3.0
Project-URL: Bug Tracker, https://github.com/shiv3679/weclimb_modules/issues
Classifier: Programming Language :: Python :: 3
Classifier: License :: OSI Approved :: GNU General Public License v3 (GPLv3)
Classifier: Operating System :: OS Independent
Requires-Python: >=3.6
Requires-Dist: xarray >=0.16.2
Requires-Dist: pandas >=1.1.5
Requires-Dist: matplotlib >=3.3.4
Requires-Dist: seaborn >=0.11.1
Requires-Dist: numpy >=1.19.5
